demultiplexer/__init__.py
demultiplexer/__main__.py
demultiplexer/demultiplexing.py
demultiplexer/file_pairs.py
demultiplexer/save_primerset.py
demultiplexer/scheme_generator.py
demultiplexer/data/primersets/Tutorial_primers.txt
demultiplexer/data/tagging_templates/Example_scheme.xlsx
demultiplexer-1.2.1.dist-info/LICENSE
demultiplexer-1.2.1.dist-info/METADATA
demultiplexer-1.2.1.dist-info/WHEEL
demultiplexer-1.2.1.dist-info/entry_points.txt
demultiplexer-1.2.1.dist-info/top_level.txt
demultiplexer-1.2.1.dist-info/RECORD
