Metadata-Version: 2.1
Name: demultiplexer
Version: 1.2.1
Summary: python script to demultiplex illumina reads tagged with the leeselab tagging scheme
Home-page: https://github.com/DominikBuchner/demultiplexer
Author: Dominik Buchner
Author-email: dominik.buchner524@googlemail.com
License: MIT
Classifier: Programming Language :: Python :: 3
Classifier: License :: OSI Approved :: MIT License
Classifier: Operating System :: OS Independent
Requires-Python: >=3.6
License-File: LICENSE
Requires-Dist: PySimpleGUI >=4.19.0
Requires-Dist: openpyxl >=3.0.3
Requires-Dist: psutil >=5.7.3
Requires-Dist: biopython >=1.78
Requires-Dist: joblib >=0.16.0
